mirmod/__init__.py
mirmod/execution_context.py
mirmod/failure_mode.py
mirmod/miranda.py
mirmod/miranda_exceptions.py
mirmod/miranda_git.py
mirmod/miranda_llm.py
mirmod/platform_versions.py
mirmod/processor.py
mirmod/processor_graph.py
mirmod/workflow_object.py
mirmod/controls/__init__.py
mirmod/controls/audio.py
mirmod/controls/chat_preview.py
mirmod/controls/chatbot.py
mirmod/controls/checkbox.py
mirmod/controls/codeeditor.py
mirmod/controls/continue_button.py
mirmod/controls/dynamic_node_compile.py
mirmod/controls/file.py
mirmod/controls/image.py
mirmod/controls/imagemask.py
mirmod/controls/markdown.py
mirmod/controls/notice.py
mirmod/controls/plotly.py
mirmod/controls/run_until_button.py
mirmod/controls/select.py
mirmod/controls/slider.py
mirmod/controls/table.py
mirmod/controls/textbox.py
mirmod/controls/video.py
mirmod/orm/__init__.py
mirmod/orm/base_orm.py
mirmod/orm/metadata.py
mirmod/security/__init__.py
mirmod/security/security_context.py
mirmod/storage/__init__.py
mirmod/storage/api.py
mirmod/storage/vault.py
mirmod/utils/__init__.py
mirmod/utils/graphml.py
mirmod/utils/logger.py
mirmod/workflow_objects/__init__.py
mirmod/workflow_objects/code_block.py
mirmod/workflow_objects/compute_policy.py
mirmod/workflow_objects/compute_resource_group.py
mirmod/workflow_objects/dashboard.py
mirmod/workflow_objects/deployment.py
mirmod/workflow_objects/docker_image.py
mirmod/workflow_objects/docker_job.py
mirmod/workflow_objects/knowledge_object.py
mirmod/workflow_objects/model.py
mirmod/workflow_objects/project.py
mirmod/workflow_objects/storage_policy.py
mirmod-5.4.1.dist-info/METADATA
mirmod-5.4.1.dist-info/WHEEL
mirmod-5.4.1.dist-info/RECORD
